{
    "episode": 11,
    "timestep": 240000,
    "reward": 1.1515080332756042,
    "length": 20,
    "time": 246.17836022377014,
    "portfolio_initial": 9903.415773242914,
    "portfolio_final": 1.1695099479939532e-172,
    "returns": -1.0,
    "sharpe": -15.75409127632091,
    "max_drawdown": 1.0,
    "trade_count": 0,
    "detailed_metrics": {
        "portfolio_values": [
            9903.415773242914,
            9533.953430383668,
            9432.61168802842,
            9354.280889509026,
            8902.682287645415,
            8244.586276257236,
            7746.675708292159,
            7366.732852762831,
            6737.715435043305,
            5196.910872470473,
            7.68505209593965e-29,
            1.3678238886711814e-76,
            1.1809427167112107e-92,
            9.608602065685797e-93,
            1.3612097040528875e-108,
            1.5142025851214404e-124,
            2.1229199032470088e-156,
            1.5796660062250348e-156,
            1.2567887008649697e-156,
            1.1695099479939532e-172
        ],
        "rewards": [
            -0.9342755675315857,
            -0.3486264944076538,
            -0.8432651162147522,
            1.6252436637878418,
            1.4227722883224487,
            1.4181231260299683,
            -3.292344093322754,
            1.4889129400253296,
            -0.9204335808753967,
            1.5354008674621582,
            0.0,
            0.0,
            -0.0,
            -0.0,
            0.0,
            -0.0,
            0.0,
            -0.0,
            -0.0,
            0.0
        ],
        "actions": [],
        "positions": [],
        "cash": [],
        "consecutive_holds": [],
        "oscillation_count": [],
        "current_cooldown": [],
        "sharpe_ratio": [],
        "max_drawdown": [],
        "portfolio_growth_rate": [],
        "successful_trade_streak": [],
        "forced_actions": [],
        "cooldown_violations": []
    }
}